README.md
setup.py
cargo_simplequery/__init__.py
cargo_simplequery/query.py
cargo_simplequery/query_test.py
cargo_simplequery/test.py
cargo_simplequery.egg-info/PKG-INFO
cargo_simplequery.egg-info/SOURCES.txt
cargo_simplequery.egg-info/dependency_links.txt
cargo_simplequery.egg-info/not-zip-safe
cargo_simplequery.egg-info/requires.txt
cargo_simplequery.egg-info/top_level.txt