Metadata-Version: 1.0
Name: cargo-simplequery
Version: 0.2.2
Summary: Wrapper around psycopg2 to build SQL queries
Home-page: https://gitlab.cargo.one/python/cargo-simplequery
Author: Mike Roetgers
Author-email: mr@cargo.one
License: MIT
Platform: UNKNOWN
